pytket/extensions/cirq/__init__.py
pytket/extensions/cirq/_metadata.py
pytket/extensions/cirq/py.typed
pytket/extensions/cirq/backends/__init__.py
pytket/extensions/cirq/backends/cirq.py
pytket/extensions/cirq/backends/cirq_convert.py
pytket/extensions/cirq/backends/cirq_utils.py
pytket_cirq-0.43.0.dist-info/licenses/LICENSE
tests/cirq_convert_test.py
tests/test_cirq_backend.py
pytket_cirq-0.43.0.dist-info/METADATA
pytket_cirq-0.43.0.dist-info/WHEEL
pytket_cirq-0.43.0.dist-info/top_level.txt
pytket_cirq-0.43.0.dist-info/RECORD
