Metadata-Version: 2.4
Name: pytket-cirq
Version: 0.43.0
Summary: Extension for pytket, providing translation to and from the Cirq framework
Author-email: TKET development team <tket-support@quantinuum.com>
Maintainer-email: TKET development team <tket-support@quantinuum.com>
License:                                  Apache License
Project-URL: documentation, https://tket.quantinuum.com/extensions/pytket-cirq/index.html
Project-URL: source, https://github.com/Quantinuum/pytket-cirq
Project-URL: tracker, https://github.com/Quantinuum/pytket-cirq/issues
Classifier: Environment :: Console
Classifier: Programming Language :: Python :: 3.11
Classifier: Programming Language :: Python :: 3.12
Classifier: Programming Language :: Python :: 3.13
Classifier: Operating System :: MacOS :: MacOS X
Classifier: Operating System :: POSIX :: Linux
Classifier: Operating System :: Microsoft :: Windows
Classifier: Intended Audience :: Developers
Classifier: Intended Audience :: Science/Research
Classifier: Topic :: Scientific/Engineering
Requires-Python: <4.0,>=3.11
License-File: LICENSE
Requires-Dist: pytket>=2.11.0
Requires-Dist: cirq-core>=1.6.0
Requires-Dist: cirq-google>=1.6.0
Dynamic: license-file
